BrowserUpMitmProxyClient/__init__.py
BrowserUpMitmProxyClient/api_client.py
BrowserUpMitmProxyClient/configuration.py
BrowserUpMitmProxyClient/exceptions.py
BrowserUpMitmProxyClient/model_utils.py
BrowserUpMitmProxyClient/rest.py
BrowserUpMitmProxyClient/api/__init__.py
BrowserUpMitmProxyClient/api/browser_up_proxy_api.py
BrowserUpMitmProxyClient/apis/__init__.py
BrowserUpMitmProxyClient/model/__init__.py
BrowserUpMitmProxyClient/model/counter.py
BrowserUpMitmProxyClient/model/custom_har_data.py
BrowserUpMitmProxyClient/model/entry.py
BrowserUpMitmProxyClient/model/entry_request.py
BrowserUpMitmProxyClient/model/entry_request_cookies.py
BrowserUpMitmProxyClient/model/entry_request_query_string.py
BrowserUpMitmProxyClient/model/entry_response.py
BrowserUpMitmProxyClient/model/entry_response_content.py
BrowserUpMitmProxyClient/model/entry_timings.py
BrowserUpMitmProxyClient/model/error.py
BrowserUpMitmProxyClient/model/har.py
BrowserUpMitmProxyClient/model/har_log.py
BrowserUpMitmProxyClient/model/har_log_creator.py
BrowserUpMitmProxyClient/model/header.py
BrowserUpMitmProxyClient/model/match_criteria.py
BrowserUpMitmProxyClient/model/name_value_pair.py
BrowserUpMitmProxyClient/model/page.py
BrowserUpMitmProxyClient/model/page_page_timings.py
BrowserUpMitmProxyClient/model/verify_result.py
BrowserUpMitmProxyClient/model/web_socket_message.py
BrowserUpMitmProxyClient/models/__init__.py
BrowserUpMitmProxyClient-1.0.1.dist-info/LICENSE
BrowserUpMitmProxyClient-1.0.1.dist-info/METADATA
BrowserUpMitmProxyClient-1.0.1.dist-info/WHEEL
BrowserUpMitmProxyClient-1.0.1.dist-info/top_level.txt
BrowserUpMitmProxyClient-1.0.1.dist-info/RECORD
