Metadata-Version: 2.1
Name: BrowserUpMitmProxyClient
Version: 1.0.1
Summary: BrowserUp MitmProxy
Home-page: https://github.com/browserup/mitmproxy
Author: BrowserUp, Inc.
Author-email: developers@browserup.com
License: UNKNOWN
Keywords: OpenAPI,OpenAPI-Generator,BrowserUp MitmProxy
Platform: UNKNOWN
Requires-Python: >=3.6
License-File: LICENSE
Requires-Dist: urllib3 (>=1.25.3)
Requires-Dist: python-dateutil
